ghclone/__init__.py
ghclone/__main__.py
github_clone-1.2.0.dist-info/LICENSE
github_clone-1.2.0.dist-info/METADATA
github_clone-1.2.0.dist-info/WHEEL
github_clone-1.2.0.dist-info/entry_points.txt
github_clone-1.2.0.dist-info/top_level.txt
github_clone-1.2.0.dist-info/RECORD
