Metadata-Version: 2.1
Name: github-clone
Version: 1.2.0
Summary: Clone any subdirectory of a GitHub repo with just the GitHub URL
Home-page: https://github.com/HR/github-clone
Author: Habib Rehman
Author-email: Hi@HabibRehman.com
License: Apache 2.0
Project-URL: Bug Tracker, https://github.com/HR/github-clone/issues
Platform: UNKNOWN
Classifier: Development Status :: 5 - Production/Stable
Classifier: Environment :: Console
Classifier: Intended Audience :: Developers
Classifier: License :: OSI Approved :: Apache Software License
Classifier: Programming Language :: Python :: 3
Classifier: Operating System :: OS Independent
Requires-Python: >=3.6
License-File: LICENSE
Requires-Dist: requests (>=2.20.0)
Requires-Dist: docopt (>=0.6.2)
